enahelper/__init__.py
enahelper/enaschema.py
enahelper/enasub.py
enahelper/enautil.py
enahelper/meta.py
gisaidhelper/__init__.py
gisaidhelper/gisaidschema.py
gisaidhelper/gisaidsub.py
gisaidhelper/gishelper.py
gisaidhelper/meta.py
subhelper-1.0.8.dist-info/LICENSE
subhelper-1.0.8.dist-info/METADATA
subhelper-1.0.8.dist-info/WHEEL
subhelper-1.0.8.dist-info/entry_points.txt
subhelper-1.0.8.dist-info/top_level.txt
subhelper-1.0.8.dist-info/RECORD
