Metadata-Version: 2.1
Name: subhelper
Version: 1.0.8
Summary: Helper scripts for submission to ena (microbial + sarscov2) and gisaid (sarscov2 only)
Home-page: https://github.com/happykhan/subhelper
Author: Nabil-Fareed Alikhan
Author-email: nabil@happykhan.com
License: UNKNOWN
Project-URL: Source, https://github.com/happykhan/subhelper
Keywords: gisaid,microbial,genomics,ena,data,submission
Platform: UNKNOWN
Classifier: Development Status :: 3 - Alpha
Classifier: Topic :: Scientific/Engineering :: Bio-Informatics
Classifier: Intended Audience :: Developers
Classifier: Intended Audience :: Science/Research
Classifier: License :: OSI Approved :: GNU General Public License v3 or later (GPLv3+)
Classifier: Natural Language :: English
Classifier: Operating System :: OS Independent
Classifier: Programming Language :: Python
Classifier: Programming Language :: Python :: 3
Classifier: Programming Language :: Python :: 3.9
Classifier: Programming Language :: Python :: 3.10
Requires-Python: >=3.9
License-File: LICENSE
Requires-Dist: biopython
Requires-Dist: marshmallow
Requires-Dist: numpy
Requires-Dist: pyaml
Requires-Dist: PyYAML
Requires-Dist: requests
Requires-Dist: openpyxl
Requires-Dist: wheel
